TracMercurial-1.0.0.11-py3.11-nspkg.pth
tracext/hg/__init__.py
tracext/hg/backend.py
tracext/hg/hooks.py
tracext/hg/locale/messages.pot
tracext/hg/locale/fr/LC_MESSAGES/tracmercurial.mo
tracext/hg/locale/fr/LC_MESSAGES/tracmercurial.po
TracMercurial-1.0.0.11.dist-info/COPYING
TracMercurial-1.0.0.11.dist-info/METADATA
TracMercurial-1.0.0.11.dist-info/WHEEL
TracMercurial-1.0.0.11.dist-info/entry_points.txt
TracMercurial-1.0.0.11.dist-info/namespace_packages.txt
TracMercurial-1.0.0.11.dist-info/top_level.txt
TracMercurial-1.0.0.11.dist-info/RECORD
